jiho/test1.py
jiho/test2.py
jiho/vgg.py
jiho-0.0.0.2.dist-info/METADATA
jiho-0.0.0.2.dist-info/WHEEL
jiho-0.0.0.2.dist-info/top_level.txt
jiho-0.0.0.2.dist-info/RECORD
