Metadata-Version: 2.1
Name: jiho
Version: 0.0.0.2
Summary: My First Test Package
Home-page: UNKNOWN
Author: jiho97
Author-email: wglh1588@gmail.com
License: MIT
Platform: UNKNOWN
Requires-Python: >=3
